mplt/__init__.py
mplt-2.0.dist-info/DESCRIPTION.rst
mplt-2.0.dist-info/METADATA
mplt-2.0.dist-info/RECORD
mplt-2.0.dist-info/WHEEL
mplt-2.0.dist-info/metadata.json
mplt-2.0.dist-info/top_level.txt
