Metadata-Version: 2.0
Name: mplt
Version: 2.0
Summary: Set of niceties wrapping matplotlib for signal processing
Home-page: http://github.com/stringhamc/mplt
Author: Craig Stringham
Author-email: stringham@ieee.org
License: MIT
Platform: UNKNOWN
Classifier: Intended Audience :: Science/Research
Requires-Dist: matplotlib
Requires-Dist: numpy
